AUTHORS.rst
CONTRIBUTING.rst
LICENSE
MANIFEST.in
README.rst
setup.cfg
setup.py
data/__init__.py
data/acqsim/__init__.py
data/acqsim/xpdUser/__init__.py
data/acqsim/xpdUser/userAnalysis/__init__.py
data/acqsim/xpdUser/userScripts/__init__.py
data/acqsim/xpdUser/userScripts/scan_rack.py
docs/Makefile
docs/make.bat
docs/source/conf.py
docs/source/index.rst
docs/source/installation.rst
docs/source/min_versions.rst
docs/source/usage.rst
docs/source/api/scanplans.rst
scanplans/__init__.py
scanplans/autoplan.py
scanplans/beamtimehelper.py
scanplans/cryostat.py
scanplans/mdgetters.py
scanplans/move_and_do.py
scanplans/tools.py
scanplans/ttseries.py
scanplans/wanda_grid_scan.py
scanplans.egg-info/PKG-INFO
scanplans.egg-info/SOURCES.txt
scanplans.egg-info/dependency_links.txt
scanplans.egg-info/entry_points.txt
scanplans.egg-info/top_level.txt