Metadata-Version: 1.2
Name: scanplans
Version: 0.1.0
Summary: Bluesky plans from Billinge group
Home-page: https://github.com/st3107/bluesky_scanplans
Author: Songsheng Tao
Author-email: st3107@columbia.edu
License: BSD (3-clause)
Platform: UNKNOWN
Classifier: Development Status :: 2 - Pre-Alpha
Classifier: Natural Language :: English
Classifier: Programming Language :: Python :: 3
Requires-Python: >=3.7
